{
	"10001": {
		"goods-id": 10001,
		"goods-name": "家居服浴衣睡袍睡衣浴袍男女秋冬季加厚法兰绒长袖可爱珊瑚绒情侣",
		"goods-price": 129.00,
		"goods-sale": 49.98,
		"size": {
			"1000101": "155(S)",
			"1000102": "160(M)",
			"1000103": "165(L)",
			"1000104": "170(XL)"
		},
		"color": {
			"id": "10001001",
			"small-pic": "img/color.png",
			"large-pic": "img/color-large.png",
			"color-type": "定位花睡袍-女-薰衣草"
		},
		"stock": 9861
	},
	"10002": {
		"goods-id": 10001,
		"goods-name": "家居服浴衣睡袍睡衣浴袍男女秋冬季加厚法兰绒长袖可爱珊瑚绒情侣",
		"goods-price": 129.00,
		"goods-sale": 45.00,
		"size": {
			"1000101": "155(S)",
			"1000102": "160(M)",
			"1000103": "165(L)",
			"1000104": "170(XL)"
		},
		"color": {
			"id": "10001001",
			"url": "img/color.png"
		}
	}
}
